<?xml version="1.0" encoding="UTF-8"?>
<!--Generated by gradle vo-dml tools 2026-02-05T17:58:28.746245921Z-->
<tap:tapschemaModel xmlns:tap="http://ivoa.net/dm/tapschema/v1"
                    xmlns:xsd="http://www.w3.org/2001/XMLSchema"
                    xmlns:xsi="http://www.w3.org/2001/XMLSchema-instance">
   <schema>
      <schema_name>DemoDM</schema_name>
      <description>A small demonstration model</description>
      <tables>
         <table>
            <table_name>PhotometricSystem</table_name>
            <table_type>table</table_type>
            <utype>DemoDM:PhotometricSystem</utype>
            <description/>
            <columns>
               <column>
                  <column_name>DemoDM.PhotometricSystem.ID</column_name>
                  <!--primary key (surrogate)-->
                  <datatype>BIGINT</datatype>
                  <description>primary key for PhotometricSystem</description>
                  <indexed>true</indexed>
                  <principal>false</principal>
                  <std>true</std>
               </column>
               <column>
                  <column_name>DemoDM.PhotometricSystem.description</column_name>
                  <!--attribute of primitiveType ivoa:string-->
                  <datatype>VARCHAR</datatype>
                  <description>String representation Photometric system</description>
                  <utype>DemoDM:PhotometricSystem.description</utype>
                  <indexed>false</indexed>
                  <principal>false</principal>
                  <std>true</std>
               </column>
               <column>
                  <column_name>DemoDM.PhotometricSystem.detectorType</column_name>
                  <!--attribute of primitiveType ivoa:integer-->
                  <datatype>INTEGER</datatype>
                  <description>Type of detector (e.g energy or photon counter)</description>
                  <utype>DemoDM:PhotometricSystem.detectorType</utype>
                  <indexed>false</indexed>
                  <principal>false</principal>
                  <std>true</std>
               </column>
            </columns>
            <fkeys/>
         </table>
         <table>
            <table_name>PhotometryFilter</table_name>
            <table_type>table</table_type>
            <utype>DemoDM:PhotometryFilter</utype>
            <description/>
            <columns>
               <column>
                  <column_name>DemoDM.PhotometryFilter.ID</column_name>
                  <!--primary key (surrogate)-->
                  <datatype>BIGINT</datatype>
                  <description>primary key for PhotometryFilter</description>
                  <indexed>true</indexed>
                  <principal>false</principal>
                  <std>true</std>
               </column>
               <column>
                  <column_name>DemoDM.PhotometryFilter.PHOTOMETRICSYSTEM_ID</column_name>
                  <datatype>BIGINT</datatype>
                  <description>foreign key column for DemoDM:PhotometricSystem composition of DemoDM:PhotometryFilter</description>
                  <utype>DemoDM:PhotometricSystem</utype>
                  <indexed>false</indexed>
                  <principal>false</principal>
                  <std>true</std>
               </column>
               <column>
                  <column_name>DemoDM.PhotometryFilter.name</column_name>
                  <!--attribute of primitiveType ivoa:string-->
                  <datatype>VARCHAR</datatype>
                  <description>Filter Name in the instrumental  configuration</description>
                  <utype>DemoDM:PhotometryFilter.name</utype>
                  <indexed>false</indexed>
                  <principal>false</principal>
                  <std>true</std>
               </column>
               <column>
                  <column_name>DemoDM.PhotometryFilter.description</column_name>
                  <!--attribute of primitiveType ivoa:string-->
                  <datatype>VARCHAR</datatype>
                  <description>Text description of the filter band</description>
                  <utype>DemoDM:PhotometryFilter.description</utype>
                  <indexed>false</indexed>
                  <principal>false</principal>
                  <std>true</std>
               </column>
               <column>
                  <column_name>DemoDM.PhotometryFilter.bandName</column_name>
                  <!--attribute of primitiveType ivoa:string-->
                  <datatype>VARCHAR</datatype>
                  <description/>
                  <utype>DemoDM:PhotometryFilter.bandName</utype>
                  <indexed>false</indexed>
                  <principal>false</principal>
                  <std>true</std>
               </column>
               <column>
                  <column_name>DemoDM.PhotometryFilter.dataValidityFrom</column_name>
                  <!--attribute of primitiveType ivoa:datetime-->
                  <datatype>TIMESTAMP</datatype>
                  <description/>
                  <utype>DemoDM:PhotometryFilter.dataValidityFrom</utype>
                  <indexed>false</indexed>
                  <principal>false</principal>
                  <std>true</std>
               </column>
               <column>
                  <column_name>DemoDM.PhotometryFilter.dataValidityTo</column_name>
                  <!--attribute of primitiveType ivoa:datetime-->
                  <datatype>TIMESTAMP</datatype>
                  <description/>
                  <utype>DemoDM:PhotometryFilter.dataValidityTo</utype>
                  <indexed>false</indexed>
                  <principal>false</principal>
                  <std>true</std>
               </column>
               <column>
                  <column_name>ivoa.PhotometryFilter.spectralLocation_value</column_name>
                  <!--attribute from dtype-->
                  <datatype>DOUBLE</datatype>
                  <description>A real value with a unit.</description>
                  <utype>ivoa:RealQuantity</utype>
                  <indexed>false</indexed>
                  <principal>false</principal>
                  <std>true</std>
               </column>
               <column>
                  <column_name>ivoa.PhotometryFilter.spectralLocation_unit</column_name>
                  <!--attribute from dtype-->
                  <datatype>VARCHAR</datatype>
                  <description>A real value with a unit.</description>
                  <utype>ivoa:RealQuantity</utype>
                  <indexed>false</indexed>
                  <principal>false</principal>
                  <std>true</std>
               </column>
            </columns>
            <fkeys>
               <foreignKey>
                  <key_id>FK_PhotometricSystem.photometryFilter</key_id>
                  <!--back reference to DemoDM:PhotometryFilter composition in DemoDM:PhotometricSystem -->
                  <target_table>PhotometricSystem</target_table>
                  <description>foreign key for DemoDM:PhotometryFilter composition in DemoDM:PhotometricSystem </description>
                  <utype>DemoDM:PhotometricSystem.photometryFilter</utype>
                  <columns>
                     <fKColumn>
                        <from_column>DemoDM.PhotometryFilter.PHOTOMETRICSYSTEM_ID</from_column>
                        <target_column>DemoDM.PhotometricSystem.ID</target_column>
                     </fKColumn>
                  </columns>
               </foreignKey>
            </fkeys>
         </table>
         <table>
            <table_name>AbstractSource</table_name>
            <table_type>table</table_type>
            <utype>DemoDM:catalog.AbstractSource</utype>
            <description/>
            <columns>
               <column>
                  <column_name>DemoDM.AbstractSource.SOURCECATALOGUE_ID</column_name>
                  <datatype>BIGINT</datatype>
                  <description>foreign key column for DemoDM:catalog.inner.SourceCatalogue composition of DemoDM:catalog.AbstractSource</description>
                  <utype>DemoDM:catalog.inner.SourceCatalogue</utype>
                  <indexed>false</indexed>
                  <principal>false</principal>
                  <std>true</std>
               </column>
               <column>
                  <column_name>DemoDM.AbstractSource.ID</column_name>
                  <!--primary/join key for subtype-->
                  <datatype>BIGINT</datatype>
                  <description>primary/join key for AbstractSource</description>
                  <indexed>true</indexed>
                  <principal>false</principal>
                  <std>true</std>
               </column>
               <column>
                  <column_name>DemoDM.AbstractSource.name</column_name>
                  <!--attribute of primitiveType ivoa:string-->
                  <datatype>VARCHAR</datatype>
                  <description/>
                  <utype>DemoDM:catalog.AbstractSource.name</utype>
                  <indexed>false</indexed>
                  <principal>false</principal>
                  <std>true</std>
               </column>
               <column>
                  <column_name>DemoDM.AbstractSource.description</column_name>
                  <!--attribute of primitiveType ivoa:string-->
                  <datatype>VARCHAR</datatype>
                  <description/>
                  <utype>DemoDM:catalog.AbstractSource.description</utype>
                  <indexed>false</indexed>
                  <principal>false</principal>
                  <std>true</std>
               </column>
               <column>
                  <column_name>DemoDM.AbstractSource.position_coord_alpha</column_name>
                  <!--attribute from dtype-->
                  <datatype>DOUBLE</datatype>
                  <description/>
                  <utype>DemoDM:catalog.SkyCoordinate</utype>
                  <indexed>false</indexed>
                  <principal>false</principal>
                  <std>true</std>
               </column>
               <column>
                  <column_name>DemoDM.AbstractSource.position_coord_delta</column_name>
                  <!--attribute from dtype-->
                  <datatype>DOUBLE</datatype>
                  <description/>
                  <utype>DemoDM:catalog.SkyCoordinate</utype>
                  <indexed>false</indexed>
                  <principal>false</principal>
                  <std>true</std>
               </column>
               <column>
                  <column_name>DemoDM.AbstractSource.position_frame</column_name>
                  <!--reference from datatype-->
                  <datatype>VARCHAR</datatype>
                  <description/>
                  <utype>DemoDM:catalog.SkyCoordinate.frame</utype>
                  <indexed>true</indexed>
                  <principal>false</principal>
                  <std>true</std>
               </column>
               <column>
                  <column_name>DemoDM.AbstractSource.classification</column_name>
                  <!--attribute of enumeration DemoDM:catalog.SourceClassification-->
                  <datatype>VARCHAR</datatype>
                  <description/>
                  <utype>DemoDM:catalog.AbstractSource.classification</utype>
                  <indexed>false</indexed>
                  <principal>false</principal>
                  <std>true</std>
               </column>
            </columns>
            <fkeys>
               <foreignKey>
                  <key_id>FK_SourceCatalogue.entry</key_id>
                  <!--back reference to DemoDM:catalog.AbstractSource composition in DemoDM:catalog.inner.SourceCatalogue -->
                  <target_table>SourceCatalogue</target_table>
                  <description>foreign key for DemoDM:catalog.AbstractSource composition in DemoDM:catalog.inner.SourceCatalogue </description>
                  <utype>DemoDM:catalog.inner.SourceCatalogue.entry</utype>
                  <columns>
                     <fKColumn>
                        <from_column>DemoDM.AbstractSource.SOURCECATALOGUE_ID</from_column>
                        <target_column>DemoDM.SourceCatalogue.ID</target_column>
                     </fKColumn>
                  </columns>
               </foreignKey>
               <foreignKey>
                  <key_id>FK_catalog.AbstractSource</key_id>
                  <target_table>AstroObject</target_table>
                  <description>join back to supertype DemoDM:catalog.AstroObject</description>
                  <utype>DemoDM:catalog.AbstractSource</utype>
                  <columns>
                     <fKColumn>
                        <from_column>DemoDM.AbstractSource.ID</from_column>
                        <target_column>DemoDM.AstroObject.ID</target_column>
                     </fKColumn>
                  </columns>
               </foreignKey>
               <foreignKey>
                  <key_id>FK_catalog.SkyCoordinate</key_id>
                  <target_table>SkyCoordinateFrame</target_table>
                  <!--dtype reference to DemoDM:catalog.SkyCoordinateFrame-->
                  <description/>
                  <utype>DemoDM:catalog.SkyCoordinate</utype>
                  <columns>
                     <fKColumn>
                        <from_column>DemoDM.AbstractSource.position_frame</from_column>
                        <target_column>DemoDM.SkyCoordinateFrame.name</target_column>
                     </fKColumn>
                  </columns>
               </foreignKey>
            </fkeys>
         </table>
         <table>
            <table_name>AstroObject</table_name>
            <table_type>table</table_type>
            <utype>DemoDM:catalog.AstroObject</utype>
            <description>Generic base class for all astronomical objects.</description>
            <columns>
               <column>
                  <column_name>DemoDM.AstroObject.ID</column_name>
                  <!--primary key (surrogate)-->
                  <datatype>BIGINT</datatype>
                  <description>primary key for AstroObject</description>
                  <indexed>true</indexed>
                  <principal>false</principal>
                  <std>true</std>
               </column>
               <column>
                  <column_name>DemoDM.AstroObject.objectType</column_name>
                  <!--attribute of primitiveType ivoa:string-->
                  <datatype>VARCHAR</datatype>
                  <description/>
                  <utype>DemoDM:catalog.AstroObject.objectType</utype>
                  <indexed>false</indexed>
                  <principal>false</principal>
                  <std>true</std>
               </column>
            </columns>
            <fkeys/>
         </table>
         <table>
            <table_name>LuminosityMeasurement</table_name>
            <table_type>table</table_type>
            <utype>DemoDM:catalog.LuminosityMeasurement</utype>
            <description/>
            <columns>
               <column>
                  <column_name>DemoDM.LuminosityMeasurement.ID</column_name>
                  <!--primary key (surrogate)-->
                  <datatype>BIGINT</datatype>
                  <description>primary key for LuminosityMeasurement</description>
                  <indexed>true</indexed>
                  <principal>false</principal>
                  <std>true</std>
               </column>
               <column>
                  <column_name>DemoDM.LuminosityMeasurement.ABSTRACTSOURCE_ID</column_name>
                  <datatype>BIGINT</datatype>
                  <description>foreign key column for DemoDM:catalog.AbstractSource composition of DemoDM:catalog.LuminosityMeasurement</description>
                  <utype>DemoDM:catalog.AbstractSource</utype>
                  <indexed>false</indexed>
                  <principal>false</principal>
                  <std>true</std>
               </column>
               <column>
                  <column_name>ivoa.LuminosityMeasurement.value_value</column_name>
                  <!--attribute from dtype-->
                  <datatype>DOUBLE</datatype>
                  <description>A real value with a unit.</description>
                  <utype>ivoa:RealQuantity</utype>
                  <indexed>false</indexed>
                  <principal>false</principal>
                  <std>true</std>
               </column>
               <column>
                  <column_name>ivoa.LuminosityMeasurement.value_unit</column_name>
                  <!--attribute from dtype-->
                  <datatype>VARCHAR</datatype>
                  <description>A real value with a unit.</description>
                  <utype>ivoa:RealQuantity</utype>
                  <indexed>false</indexed>
                  <principal>false</principal>
                  <std>true</std>
               </column>
               <column>
                  <column_name>ivoa.LuminosityMeasurement.error_value</column_name>
                  <!--attribute from dtype-->
                  <datatype>DOUBLE</datatype>
                  <description>A real value with a unit.</description>
                  <utype>ivoa:RealQuantity</utype>
                  <indexed>false</indexed>
                  <principal>false</principal>
                  <std>true</std>
               </column>
               <column>
                  <column_name>ivoa.LuminosityMeasurement.error_unit</column_name>
                  <!--attribute from dtype-->
                  <datatype>VARCHAR</datatype>
                  <description>A real value with a unit.</description>
                  <utype>ivoa:RealQuantity</utype>
                  <indexed>false</indexed>
                  <principal>false</principal>
                  <std>true</std>
               </column>
               <column>
                  <column_name>DemoDM.LuminosityMeasurement.description</column_name>
                  <!--attribute of primitiveType ivoa:string-->
                  <datatype>VARCHAR</datatype>
                  <description/>
                  <utype>DemoDM:catalog.LuminosityMeasurement.description</utype>
                  <indexed>false</indexed>
                  <principal>false</principal>
                  <std>true</std>
               </column>
               <column>
                  <column_name>DemoDM.LuminosityMeasurement.type</column_name>
                  <!--attribute of enumeration DemoDM:catalog.LuminosityType-->
                  <datatype>VARCHAR</datatype>
                  <description/>
                  <utype>DemoDM:catalog.LuminosityMeasurement.type</utype>
                  <indexed>false</indexed>
                  <principal>false</principal>
                  <std>true</std>
               </column>
               <column>
                  <column_name>DemoDM.LuminosityMeasurement.filter</column_name>
                  <!--reference to DemoDM:PhotometryFilter-->
                  <datatype>BIGINT</datatype>
                  <description/>
                  <utype>DemoDM:catalog.LuminosityMeasurement.filter</utype>
                  <indexed>false</indexed>
                  <principal>false</principal>
                  <std>true</std>
               </column>
            </columns>
            <fkeys>
               <foreignKey>
                  <key_id>FK_LuminosityMeasurement.filter</key_id>
                  <!--reference to DemoDM:PhotometryFilter -->
                  <target_table>PhotometryFilter</target_table>
                  <description/>
                  <utype>DemoDM:catalog.LuminosityMeasurement.filter</utype>
                  <columns>
                     <fKColumn>
                        <from_column>DemoDM.LuminosityMeasurement.filter</from_column>
                        <target_column>DemoDM.PhotometryFilter.ID</target_column>
                     </fKColumn>
                  </columns>
               </foreignKey>
               <foreignKey>
                  <key_id>FK_AbstractSource.luminosity</key_id>
                  <!--back reference to DemoDM:catalog.LuminosityMeasurement composition in DemoDM:catalog.AbstractSource -->
                  <target_table>AbstractSource</target_table>
                  <description>foreign key for DemoDM:catalog.LuminosityMeasurement composition in DemoDM:catalog.AbstractSource </description>
                  <utype>DemoDM:catalog.AbstractSource.luminosity</utype>
                  <columns>
                     <fKColumn>
                        <from_column>DemoDM.LuminosityMeasurement.ABSTRACTSOURCE_ID</from_column>
                        <target_column>DemoDM.AbstractSource.ID</target_column>
                     </fKColumn>
                  </columns>
               </foreignKey>
            </fkeys>
         </table>
         <table>
            <table_name>SDSSSource</table_name>
            <table_type>table</table_type>
            <utype>DemoDM:catalog.SDSSSource</utype>
            <description/>
            <columns>
               <column>
                  <column_name>DemoDM.SDSSSource.ID</column_name>
                  <!--primary/join key for subtype-->
                  <datatype>BIGINT</datatype>
                  <description>primary/join key for SDSSSource</description>
                  <indexed>true</indexed>
                  <principal>false</principal>
                  <std>true</std>
               </column>
            </columns>
            <fkeys>
               <foreignKey>
                  <key_id>FK_catalog.SDSSSource</key_id>
                  <target_table>AbstractSource</target_table>
                  <description>join back to supertype DemoDM:catalog.AbstractSource</description>
                  <utype>DemoDM:catalog.SDSSSource</utype>
                  <columns>
                     <fKColumn>
                        <from_column>DemoDM.SDSSSource.ID</from_column>
                        <target_column>DemoDM.AbstractSource.ID</target_column>
                     </fKColumn>
                  </columns>
               </foreignKey>
            </fkeys>
         </table>
         <table>
            <table_name>SkyCoordinateFrame</table_name>
            <table_type>table</table_type>
            <utype>DemoDM:catalog.SkyCoordinateFrame</utype>
            <description/>
            <columns>
               <column>
                  <column_name>DemoDM.SkyCoordinateFrame.name</column_name>
                  <!--attribute of primitiveType ivoa:string-->
                  <datatype>VARCHAR</datatype>
                  <description/>
                  <utype>DemoDM:catalog.SkyCoordinateFrame.name</utype>
                  <indexed>true</indexed>
                  <principal>false</principal>
                  <std>true</std>
               </column>
               <column>
                  <column_name>DemoDM.SkyCoordinateFrame.documentURI</column_name>
                  <!--attribute of primitiveType ivoa:anyURI-->
                  <datatype>VARCHAR</datatype>
                  <description/>
                  <utype>DemoDM:catalog.SkyCoordinateFrame.documentURI</utype>
                  <indexed>false</indexed>
                  <principal>false</principal>
                  <std>true</std>
               </column>
               <column>
                  <column_name>DemoDM.SkyCoordinateFrame.equinox</column_name>
                  <!--attribute of primitiveType ivoa:string-->
                  <datatype>VARCHAR</datatype>
                  <description/>
                  <utype>DemoDM:catalog.SkyCoordinateFrame.equinox</utype>
                  <indexed>false</indexed>
                  <principal>false</principal>
                  <std>true</std>
               </column>
               <column>
                  <column_name>DemoDM.SkyCoordinateFrame.system</column_name>
                  <!--attribute of primitiveType ivoa:string-->
                  <datatype>VARCHAR</datatype>
                  <description/>
                  <utype>DemoDM:catalog.SkyCoordinateFrame.system</utype>
                  <indexed>false</indexed>
                  <principal>false</principal>
                  <std>true</std>
               </column>
            </columns>
            <fkeys/>
         </table>
         <table>
            <table_name>Source</table_name>
            <table_type>table</table_type>
            <utype>DemoDM:catalog.Source</utype>
            <description/>
            <columns>
               <column>
                  <column_name>DemoDM.Source.ID</column_name>
                  <!--primary/join key for subtype-->
                  <datatype>BIGINT</datatype>
                  <description>primary/join key for Source</description>
                  <indexed>true</indexed>
                  <principal>false</principal>
                  <std>true</std>
               </column>
            </columns>
            <fkeys>
               <foreignKey>
                  <key_id>FK_catalog.Source</key_id>
                  <target_table>AbstractSource</target_table>
                  <description>join back to supertype DemoDM:catalog.AbstractSource</description>
                  <utype>DemoDM:catalog.Source</utype>
                  <columns>
                     <fKColumn>
                        <from_column>DemoDM.Source.ID</from_column>
                        <target_column>DemoDM.AbstractSource.ID</target_column>
                     </fKColumn>
                  </columns>
               </foreignKey>
            </fkeys>
         </table>
         <table>
            <table_name>TwoMassSource</table_name>
            <table_type>table</table_type>
            <utype>DemoDM:catalog.TwoMassSource</utype>
            <description/>
            <columns>
               <column>
                  <column_name>DemoDM.TwoMassSource.ID</column_name>
                  <!--primary/join key for subtype-->
                  <datatype>BIGINT</datatype>
                  <description>primary/join key for TwoMassSource</description>
                  <indexed>true</indexed>
                  <principal>false</principal>
                  <std>true</std>
               </column>
            </columns>
            <fkeys>
               <foreignKey>
                  <key_id>FK_catalog.TwoMassSource</key_id>
                  <target_table>AbstractSource</target_table>
                  <description>join back to supertype DemoDM:catalog.AbstractSource</description>
                  <utype>DemoDM:catalog.TwoMassSource</utype>
                  <columns>
                     <fKColumn>
                        <from_column>DemoDM.TwoMassSource.ID</from_column>
                        <target_column>DemoDM.AbstractSource.ID</target_column>
                     </fKColumn>
                  </columns>
               </foreignKey>
            </fkeys>
         </table>
         <table>
            <table_name>Testing</table_name>
            <table_type>table</table_type>
            <utype>DemoDM:catalog.inner.Testing</utype>
            <description/>
            <columns>
               <column>
                  <column_name>DemoDM.Testing.ID</column_name>
                  <!--primary key (surrogate)-->
                  <datatype>BIGINT</datatype>
                  <description>primary key for Testing</description>
                  <indexed>true</indexed>
                  <principal>false</principal>
                  <std>true</std>
               </column>
               <column>
                  <column_name>DemoDM.Testing.SOURCECATALOGUE_ID</column_name>
                  <datatype>BIGINT</datatype>
                  <description>foreign key column for DemoDM:catalog.inner.SourceCatalogue composition of DemoDM:catalog.inner.Testing</description>
                  <utype>DemoDM:catalog.inner.SourceCatalogue</utype>
                  <indexed>false</indexed>
                  <principal>false</principal>
                  <std>true</std>
               </column>
               <column>
                  <column_name>DemoDM.Testing.plain</column_name>
                  <!--attribute of primitiveType ivoa:string-->
                  <datatype>VARCHAR</datatype>
                  <description>a single string</description>
                  <utype>DemoDM:catalog.inner.Testing.plain</utype>
                  <indexed>false</indexed>
                  <principal>false</principal>
                  <std>true</std>
               </column>
               <column>
                  <column_name>DemoDM.Testing.unbounded</column_name>
                  <!--attribute of primitiveType ivoa:string-->
                  <datatype>VARCHAR</datatype>
                  <description>an array with many elements</description>
                  <utype>DemoDM:catalog.inner.Testing.unbounded</utype>
                  <indexed>false</indexed>
                  <principal>false</principal>
                  <std>true</std>
               </column>
               <column>
                  <column_name>DemoDM.Testing.apoint_alpha</column_name>
                  <!--attribute from dtype-->
                  <datatype>DOUBLE</datatype>
                  <description>location on the sky in spherical coordinates</description>
                  <utype>DemoDM:Point</utype>
                  <indexed>false</indexed>
                  <principal>false</principal>
                  <std>true</std>
               </column>
               <column>
                  <column_name>DemoDM.Testing.apoint_delta</column_name>
                  <!--attribute from dtype-->
                  <datatype>DOUBLE</datatype>
                  <description>location on the sky in spherical coordinates</description>
                  <utype>DemoDM:Point</utype>
                  <indexed>false</indexed>
                  <principal>false</principal>
                  <std>true</std>
               </column>
               <column>
                  <column_name>DemoDM.Testing.acircle_center_alpha</column_name>
                  <!--attribute from dtype-->
                  <datatype>DOUBLE</datatype>
                  <description>a circular region on the sky</description>
                  <utype>DemoDM:Circle</utype>
                  <indexed>false</indexed>
                  <principal>false</principal>
                  <std>true</std>
               </column>
               <column>
                  <column_name>DemoDM.Testing.acircle_center_delta</column_name>
                  <!--attribute from dtype-->
                  <datatype>DOUBLE</datatype>
                  <description>a circular region on the sky</description>
                  <utype>DemoDM:Circle</utype>
                  <indexed>false</indexed>
                  <principal>false</principal>
                  <std>true</std>
               </column>
               <column>
                  <column_name>DemoDM.Testing.acircle_radius</column_name>
                  <!--attribute from dtype-->
                  <datatype>DOUBLE</datatype>
                  <description>a circular region on the sky</description>
                  <utype>DemoDM:Circle</utype>
                  <indexed>false</indexed>
                  <principal>false</principal>
                  <std>true</std>
               </column>
               <column>
                  <column_name>DemoDM.Testing.apoly_points_alpha</column_name>
                  <!--attribute from dtype-->
                  <datatype>DOUBLE</datatype>
                  <description>a simple polygon region on the sky defined a sequence of points connected by great-circle segments</description>
                  <utype>DemoDM:Polygon</utype>
                  <indexed>false</indexed>
                  <principal>false</principal>
                  <std>true</std>
               </column>
               <column>
                  <column_name>DemoDM.Testing.apoly_points_delta</column_name>
                  <!--attribute from dtype-->
                  <datatype>DOUBLE</datatype>
                  <description>a simple polygon region on the sky defined a sequence of points connected by great-circle segments</description>
                  <utype>DemoDM:Polygon</utype>
                  <indexed>false</indexed>
                  <principal>false</principal>
                  <std>true</std>
               </column>
            </columns>
            <fkeys>
               <foreignKey>
                  <key_id>FK_SourceCatalogue.aTestMore</key_id>
                  <!--back reference to DemoDM:catalog.inner.Testing composition in DemoDM:catalog.inner.SourceCatalogue -->
                  <target_table>SourceCatalogue</target_table>
                  <description>foreign key for DemoDM:catalog.inner.Testing composition in DemoDM:catalog.inner.SourceCatalogue </description>
                  <utype>DemoDM:catalog.inner.SourceCatalogue.aTestMore</utype>
                  <columns>
                     <fKColumn>
                        <from_column>DemoDM.Testing.SOURCECATALOGUE_ID</from_column>
                        <target_column>DemoDM.SourceCatalogue.ID</target_column>
                     </fKColumn>
                  </columns>
               </foreignKey>
            </fkeys>
         </table>
         <table>
            <table_name>SourceCatalogue</table_name>
            <table_type>table</table_type>
            <utype>DemoDM:catalog.inner.SourceCatalogue</utype>
            <description/>
            <columns>
               <column>
                  <column_name>DemoDM.SourceCatalogue.ID</column_name>
                  <!--primary key (surrogate)-->
                  <datatype>BIGINT</datatype>
                  <description>primary key for SourceCatalogue</description>
                  <indexed>true</indexed>
                  <principal>false</principal>
                  <std>true</std>
               </column>
               <column>
                  <column_name>DemoDM.SourceCatalogue.name</column_name>
                  <!--attribute of primitiveType ivoa:string-->
                  <datatype>VARCHAR</datatype>
                  <description>the name of the catalogue</description>
                  <utype>DemoDM:catalog.inner.SourceCatalogue.name</utype>
                  <indexed>false</indexed>
                  <principal>false</principal>
                  <std>true</std>
               </column>
            </columns>
            <fkeys/>
         </table>
      </tables>
   </schema>
</tap:tapschemaModel>
