<?xml version="1.0" encoding="UTF-8"?>
<vo-dml:model xmlns:vo-dml="http://www.ivoa.net/xml/VODML/v1" 
              xmlns:xsi="http://www.w3.org/2001/XMLSchema-instance"
              xsi:schemaLocation="http://www.ivoa.net/xml/VODML/v1 https://www.ivoa.net/xml/VODML/vo-dml-v1.xsd" 
              vodmlVersion="1.1">	<!-- file generated from VODSL - needs validatation against v1.1 of schema  --> 
      <name>DemoDM</name>
      <description>A small demonstration model</description> 
      <uri/>
      <title></title>
      <author>me</author>
      <version>1.0</version>
      <lastModified>2026-02-04T17:09:05Z</lastModified>
      <import>
        <name>ivoa</name>
        <version>1.0</version>
        <url>IVOA-v1.0.vo-dml.xml</url>
        <documentationURL>not known</documentationURL>
      </import>
            <dataType>
              <vodml-id>Point</vodml-id>
              <name>Point</name>
              <description>location on the sky in spherical coordinates</description>	    
            <attribute>
              <vodml-id>Point.alpha</vodml-id>
              <name>alpha</name>
              <description>longitude angle</description>	    
              <datatype>
                 <vodml-ref>ivoa:real</vodml-ref>
              </datatype>
              <multiplicity>
                <minOccurs>1</minOccurs>
                <maxOccurs>1</maxOccurs>
              </multiplicity>
            </attribute>
            <attribute>
              <vodml-id>Point.delta</vodml-id>
              <name>delta</name>
              <description>latitude angle</description>	    
              <datatype>
                 <vodml-ref>ivoa:real</vodml-ref>
              </datatype>
              <multiplicity>
                <minOccurs>1</minOccurs>
                <maxOccurs>1</maxOccurs>
              </multiplicity>
            </attribute>
            </dataType>
            <dataType abstract="true">
              <vodml-id>Shape</vodml-id>
              <name>Shape</name>
              <description>base type of all shapes</description>	    
            </dataType>
            <dataType>
              <vodml-id>Circle</vodml-id>
              <name>Circle</name>
              <description>a circular region on the sky</description>	    
               <extends>
                  <vodml-ref>DemoDM:Shape</vodml-ref>
               </extends>
            <attribute>
              <vodml-id>Circle.center</vodml-id>
              <name>center</name>
              <description>the centre of the circle</description>	    
              <datatype>
                 <vodml-ref>DemoDM:Point</vodml-ref>
              </datatype>
              <multiplicity>
                <minOccurs>1</minOccurs>
                <maxOccurs>1</maxOccurs>
              </multiplicity>
            </attribute>
            <attribute>
              <vodml-id>Circle.radius</vodml-id>
              <name>radius</name>
              <description>the radius of the circle</description>	    
              <datatype>
                 <vodml-ref>ivoa:real</vodml-ref>
              </datatype>
              <multiplicity>
                <minOccurs>1</minOccurs>
                <maxOccurs>1</maxOccurs>
              </multiplicity>
            </attribute>
            </dataType>
            <dataType>
              <vodml-id>MultiShape</vodml-id>
              <name>MultiShape</name>
              <description>multiple simple shapes describing regions as a single value</description>	    
            <attribute>
              <vodml-id>MultiShape.shapes</vodml-id>
              <name>shapes</name>
              <description></description>	    
              <datatype>
                 <vodml-ref>DemoDM:Shape</vodml-ref>
              </datatype>
              <multiplicity>
                <minOccurs>1</minOccurs>
                <maxOccurs>-1</maxOccurs>
              </multiplicity>
            </attribute>
            </dataType>
            <dataType>
              <vodml-id>Polygon</vodml-id>
              <name>Polygon</name>
              <description>a simple polygon region on the sky defined a sequence of points connected by great-circle segments</description>	    
               <extends>
                  <vodml-ref>DemoDM:Shape</vodml-ref>
               </extends>
            <attribute>
              <vodml-id>Polygon.points</vodml-id>
              <name>points</name>
              <description></description>	    
              <datatype>
                 <vodml-ref>DemoDM:Point</vodml-ref>
              </datatype>
              <multiplicity>
                <minOccurs>1</minOccurs>
                <maxOccurs>-1</maxOccurs>
              </multiplicity>
            </attribute>
            </dataType>
            <objectType>
               <vodml-id>PhotometricSystem</vodml-id>
               <name>PhotometricSystem</name>
               <description></description>	    
               <attribute>
                 <vodml-id>PhotometricSystem.description</vodml-id>
                 <name>description</name>
                 <description>String representation Photometric system</description>	    
                 <datatype>
                    <vodml-ref>ivoa:string</vodml-ref>
                 </datatype>
                 <multiplicity>
                   <minOccurs>0</minOccurs>
                   <maxOccurs>1</maxOccurs>
                 </multiplicity>
               </attribute>
               <attribute>
                 <vodml-id>PhotometricSystem.detectorType</vodml-id>
                 <name>detectorType</name>
                 <description>Type of detector (e.g energy or photon counter)</description>	    
                 <datatype>
                    <vodml-ref>ivoa:integer</vodml-ref>
                 </datatype>
                 <multiplicity>
                   <minOccurs>1</minOccurs>
                   <maxOccurs>1</maxOccurs>
                 </multiplicity>
               </attribute>
               <composition>
                 <vodml-id>PhotometricSystem.photometryFilter</vodml-id>
                 <name>photometryFilter</name>
                 <description></description>	    
                 <datatype>
                    <vodml-ref>DemoDM:PhotometryFilter</vodml-ref>
                 </datatype>
                 <multiplicity>
                   <minOccurs>1</minOccurs>
                   <maxOccurs>-1</maxOccurs>
                 </multiplicity>
               </composition>
            </objectType>
            <objectType>
               <vodml-id>PhotometryFilter</vodml-id>
               <name>PhotometryFilter</name>
               <description></description>	    
               <attribute>
                 <vodml-id>PhotometryFilter.name</vodml-id>
                 <name>name</name>
                 <description>Filter Name in the instrumental  configuration</description>	    
                 <datatype>
                    <vodml-ref>ivoa:string</vodml-ref>
                 </datatype>
                 <multiplicity>
                   <minOccurs>1</minOccurs>
                   <maxOccurs>1</maxOccurs>
                 </multiplicity>
               </attribute>
               <attribute>
                 <vodml-id>PhotometryFilter.description</vodml-id>
                 <name>description</name>
                 <description>Text description of the filter band</description>	    
                 <datatype>
                    <vodml-ref>ivoa:string</vodml-ref>
                 </datatype>
                 <multiplicity>
                   <minOccurs>1</minOccurs>
                   <maxOccurs>1</maxOccurs>
                 </multiplicity>
               </attribute>
               <attribute>
                 <vodml-id>PhotometryFilter.bandName</vodml-id>
                 <name>bandName</name>
                 <description></description>	    
                 <datatype>
                    <vodml-ref>ivoa:string</vodml-ref>
                 </datatype>
                 <multiplicity>
                   <minOccurs>1</minOccurs>
                   <maxOccurs>1</maxOccurs>
                 </multiplicity>
               </attribute>
               <attribute>
                 <vodml-id>PhotometryFilter.dataValidityFrom</vodml-id>
                 <name>dataValidityFrom</name>
                 <description></description>	    
                 <datatype>
                    <vodml-ref>ivoa:datetime</vodml-ref>
                 </datatype>
                 <multiplicity>
                   <minOccurs>1</minOccurs>
                   <maxOccurs>1</maxOccurs>
                 </multiplicity>
               </attribute>
               <attribute>
                 <vodml-id>PhotometryFilter.dataValidityTo</vodml-id>
                 <name>dataValidityTo</name>
                 <description></description>	    
                 <datatype>
                    <vodml-ref>ivoa:datetime</vodml-ref>
                 </datatype>
                 <multiplicity>
                   <minOccurs>1</minOccurs>
                   <maxOccurs>1</maxOccurs>
                 </multiplicity>
               </attribute>
               <attribute>
                 <vodml-id>PhotometryFilter.spectralLocation</vodml-id>
                 <name>spectralLocation</name>
                 <description></description>	    
                 <datatype>
                    <vodml-ref>ivoa:RealQuantity</vodml-ref>
                 </datatype>
                 <multiplicity>
                   <minOccurs>1</minOccurs>
                   <maxOccurs>1</maxOccurs>
                 </multiplicity>
               </attribute>
            </objectType>
            <package>
               <vodml-id>catalog</vodml-id>
               <name>catalog</name>
               <description></description>	    
                         <enumeration>
                            <vodml-id>catalog.LuminosityType</vodml-id>
                            <name>LuminosityType</name>
                            <description>vale</description>	    
                               <literal>
                                 <vodml-id>catalog.LuminosityType.magnitude</vodml-id>
                                 <name>magnitude</name>
                                 <description></description>	    
                               </literal>	
                               <literal>
                                 <vodml-id>catalog.LuminosityType.flux</vodml-id>
                                 <name>flux</name>
                                 <description></description>	    
                               </literal>	
                         </enumeration>
                         <enumeration>
                            <vodml-id>catalog.SourceClassification</vodml-id>
                            <name>SourceClassification</name>
                            <description></description>	    
                               <literal>
                                 <vodml-id>catalog.SourceClassification.target</vodml-id>
                                 <name>target</name>
                                 <description></description>	    
                               </literal>	
                               <literal>
                                 <vodml-id>catalog.SourceClassification.calibrator</vodml-id>
                                 <name>calibrator</name>
                                 <description></description>	    
                               </literal>	
                         </enumeration>
                         <dataType>
                           <vodml-id>catalog.AlignedEllipse</vodml-id>
                           <name>AlignedEllipse</name>
                           <description></description>	    
                            <extends>
                               <vodml-ref>DemoDM:catalog.SkyError</vodml-ref>
                            </extends>
                         <attribute>
                           <vodml-id>catalog.AlignedEllipse.longError</vodml-id>
                           <name>longError</name>
                           <description></description>	    
                           <datatype>
                              <vodml-ref>ivoa:real</vodml-ref>
                           </datatype>
                           <multiplicity>
                             <minOccurs>1</minOccurs>
                             <maxOccurs>1</maxOccurs>
                           </multiplicity>
                         </attribute>
                         <attribute>
                           <vodml-id>catalog.AlignedEllipse.latError</vodml-id>
                           <name>latError</name>
                           <description></description>	    
                           <datatype>
                              <vodml-ref>ivoa:real</vodml-ref>
                           </datatype>
                           <multiplicity>
                             <minOccurs>1</minOccurs>
                             <maxOccurs>1</maxOccurs>
                           </multiplicity>
                         </attribute>
                         </dataType>
                         <dataType>
                           <vodml-id>catalog.CircleError</vodml-id>
                           <name>CircleError</name>
                           <description></description>	    
                            <extends>
                               <vodml-ref>DemoDM:catalog.SkyError</vodml-ref>
                            </extends>
                         <attribute>
                           <vodml-id>catalog.CircleError.radius</vodml-id>
                           <name>radius</name>
                           <description></description>	    
                           <datatype>
                              <vodml-ref>ivoa:real</vodml-ref>
                           </datatype>
                           <multiplicity>
                             <minOccurs>1</minOccurs>
                             <maxOccurs>1</maxOccurs>
                           </multiplicity>
                         </attribute>
                         </dataType>
                         <dataType>
                           <vodml-id>catalog.GenericEllipse</vodml-id>
                           <name>GenericEllipse</name>
                           <description></description>	    
                            <extends>
                               <vodml-ref>DemoDM:catalog.SkyError</vodml-ref>
                            </extends>
                         <attribute>
                           <vodml-id>catalog.GenericEllipse.major</vodml-id>
                           <name>major</name>
                           <description>major axis of error ellipse</description>	    
                           <datatype>
                              <vodml-ref>ivoa:real</vodml-ref>
                           </datatype>
                           <multiplicity>
                             <minOccurs>1</minOccurs>
                             <maxOccurs>1</maxOccurs>
                           </multiplicity>
                         </attribute>
                         <attribute>
                           <vodml-id>catalog.GenericEllipse.minor</vodml-id>
                           <name>minor</name>
                           <description>minor axis of error ellipse</description>	    
                           <datatype>
                              <vodml-ref>ivoa:real</vodml-ref>
                           </datatype>
                           <multiplicity>
                             <minOccurs>1</minOccurs>
                             <maxOccurs>1</maxOccurs>
                           </multiplicity>
                         </attribute>
                         <attribute>
                           <vodml-id>catalog.GenericEllipse.pa</vodml-id>
                           <name>pa</name>
                           <description>Position angle of error ellipse in coordinate system of position.</description>	    
                           <datatype>
                              <vodml-ref>ivoa:real</vodml-ref>
                           </datatype>
                           <multiplicity>
                             <minOccurs>1</minOccurs>
                             <maxOccurs>1</maxOccurs>
                           </multiplicity>
                         </attribute>
                         </dataType>
                         <dataType>
                           <vodml-id>catalog.SkyCoordinate</vodml-id>
                           <name>SkyCoordinate</name>
                           <description></description>	    
                            <constraint>
                               <description><![CDATA[0<=self.longitude.value < 360]]></description>
                               <!-- <language>Natural</language> -->
                            </constraint>
                            <constraint>
                               <description><![CDATA[-90<=self.latitude.value<=90]]></description>
                               <!-- <language>Natural</language> -->
                            </constraint>
                         <attribute>
                           <vodml-id>catalog.SkyCoordinate.coord</vodml-id>
                           <name>coord</name>
                           <description></description>	    
                           <datatype>
                              <vodml-ref>DemoDM:Point</vodml-ref>
                           </datatype>
                           <multiplicity>
                             <minOccurs>1</minOccurs>
                             <maxOccurs>1</maxOccurs>
                           </multiplicity>
                         </attribute>
                         <reference>
                           <vodml-id>catalog.SkyCoordinate.frame</vodml-id>
                           <name>frame</name>
                           <description></description>	    
                           <datatype>
                             <vodml-ref>DemoDM:catalog.SkyCoordinateFrame</vodml-ref>
                           </datatype>
                           <multiplicity>
                             <minOccurs>1</minOccurs>
                             <maxOccurs>1</maxOccurs>
                           </multiplicity>
                         </reference>
                         </dataType>
                         <dataType abstract="true">
                           <vodml-id>catalog.SkyError</vodml-id>
                           <name>SkyError</name>
                           <description>Error of a position on the sky.</description>	    
                         </dataType>
                         <objectType abstract="true">
                            <vodml-id>catalog.AbstractSource</vodml-id>
                            <name>AbstractSource</name>
                            <description></description>	    
                            <extends>
                               <vodml-ref>DemoDM:catalog.AstroObject</vodml-ref>
                            </extends>
                            <attribute>
                              <vodml-id>catalog.AbstractSource.name</vodml-id>
                              <name>name</name>
                              <description></description>	    
                              <datatype>
                                 <vodml-ref>ivoa:string</vodml-ref>
                              </datatype>
                              <multiplicity>
                                <minOccurs>1</minOccurs>
                                <maxOccurs>1</maxOccurs>
                              </multiplicity>
                            </attribute>
                            <attribute>
                              <vodml-id>catalog.AbstractSource.description</vodml-id>
                              <name>description</name>
                              <description></description>	    
                              <datatype>
                                 <vodml-ref>ivoa:string</vodml-ref>
                              </datatype>
                              <multiplicity>
                                <minOccurs>0</minOccurs>
                                <maxOccurs>1</maxOccurs>
                              </multiplicity>
                            </attribute>
                            <attribute>
                              <vodml-id>catalog.AbstractSource.position</vodml-id>
                              <name>position</name>
                              <description></description>	    
                              <datatype>
                                 <vodml-ref>DemoDM:catalog.SkyCoordinate</vodml-ref>
                              </datatype>
                              <multiplicity>
                                <minOccurs>1</minOccurs>
                                <maxOccurs>1</maxOccurs>
                              </multiplicity>
                            </attribute>
                            <attribute>
                              <vodml-id>catalog.AbstractSource.positionError</vodml-id>
                              <name>positionError</name>
                              <description></description>	    
                              <datatype>
                                 <vodml-ref>DemoDM:catalog.SkyError</vodml-ref>
                              </datatype>
                              <multiplicity>
                                <minOccurs>0</minOccurs>
                                <maxOccurs>1</maxOccurs>
                              </multiplicity>
                            </attribute>
                            <attribute>
                              <vodml-id>catalog.AbstractSource.classification</vodml-id>
                              <name>classification</name>
                              <description></description>	    
                              <datatype>
                                 <vodml-ref>DemoDM:catalog.SourceClassification</vodml-ref>
                              </datatype>
                              <multiplicity>
                                <minOccurs>1</minOccurs>
                                <maxOccurs>1</maxOccurs>
                              </multiplicity>
                            </attribute>
                            <composition>
                              <vodml-id>catalog.AbstractSource.luminosity</vodml-id>
                              <name>luminosity</name>
                              <description></description>	    
                              <datatype>
                                 <vodml-ref>DemoDM:catalog.LuminosityMeasurement</vodml-ref>
                              </datatype>
                              <multiplicity>
                                <minOccurs>0</minOccurs>
                                <maxOccurs>-1</maxOccurs>
                              </multiplicity>
                            </composition>
                         </objectType>
                         <objectType abstract="true">
                            <vodml-id>catalog.AstroObject</vodml-id>
                            <name>AstroObject</name>
                            <description>Generic base class for all astronomical objects.</description>	    
                            <attribute>
                              <vodml-id>catalog.AstroObject.objectType</vodml-id>
                              <name>objectType</name>
                              <description></description>	    
                              <datatype>
                                 <vodml-ref>ivoa:string</vodml-ref>
                              </datatype>
                              <multiplicity>
                                <minOccurs>0</minOccurs>
                                <maxOccurs>1</maxOccurs>
                              </multiplicity>
                            <semanticconcept>
                              <vocabularyURI>http://www.ivoa.net/rdf/object-type</vocabularyURI>
                            </semanticconcept>
                            </attribute>
                         </objectType>
                         <objectType>
                            <vodml-id>catalog.LuminosityMeasurement</vodml-id>
                            <name>LuminosityMeasurement</name>
                            <description></description>	    
                            <attribute>
                              <vodml-id>catalog.LuminosityMeasurement.value</vodml-id>
                              <name>value</name>
                              <description></description>	    
                              <datatype>
                                 <vodml-ref>ivoa:RealQuantity</vodml-ref>
                              </datatype>
                              <multiplicity>
                                <minOccurs>1</minOccurs>
                                <maxOccurs>1</maxOccurs>
                              </multiplicity>
                            </attribute>
                            <attribute>
                              <vodml-id>catalog.LuminosityMeasurement.error</vodml-id>
                              <name>error</name>
                              <description></description>	    
                              <datatype>
                                 <vodml-ref>ivoa:RealQuantity</vodml-ref>
                              </datatype>
                              <multiplicity>
                                <minOccurs>0</minOccurs>
                                <maxOccurs>1</maxOccurs>
                              </multiplicity>
                            </attribute>
                            <attribute>
                              <vodml-id>catalog.LuminosityMeasurement.description</vodml-id>
                              <name>description</name>
                              <description></description>	    
                              <datatype>
                                 <vodml-ref>ivoa:string</vodml-ref>
                              </datatype>
                              <multiplicity>
                                <minOccurs>0</minOccurs>
                                <maxOccurs>1</maxOccurs>
                              </multiplicity>
                            </attribute>
                            <attribute>
                              <vodml-id>catalog.LuminosityMeasurement.type</vodml-id>
                              <name>type</name>
                              <description></description>	    
                              <datatype>
                                 <vodml-ref>DemoDM:catalog.LuminosityType</vodml-ref>
                              </datatype>
                              <multiplicity>
                                <minOccurs>1</minOccurs>
                                <maxOccurs>1</maxOccurs>
                              </multiplicity>
                            </attribute>
                            <reference>
                              <vodml-id>catalog.LuminosityMeasurement.filter</vodml-id>
                              <name>filter</name>
                              <description></description>	    
                              <datatype>
                                <vodml-ref>DemoDM:PhotometryFilter</vodml-ref>
                              </datatype>
                              <multiplicity>
                                <minOccurs>1</minOccurs>
                                <maxOccurs>1</maxOccurs>
                              </multiplicity>
                            </reference>
                         </objectType>
                         <objectType>
                            <vodml-id>catalog.SDSSSource</vodml-id>
                            <name>SDSSSource</name>
                            <description></description>	    
                            <extends>
                               <vodml-ref>DemoDM:catalog.AbstractSource</vodml-ref>
                            </extends>
                            <constraint xsi:type="vo-dml:SubsettedRole">
                               <role>
                                  <vodml-ref>DemoDM:catalog.AbstractSource.positionError</vodml-ref>
                               </role>
                               <datatype>
                                  <vodml-ref>DemoDM:catalog.AlignedEllipse</vodml-ref>
                               </datatype>
                            </constraint>
                         </objectType>
                         <objectType>
                            <vodml-id>catalog.SkyCoordinateFrame</vodml-id>
                            <name>SkyCoordinateFrame</name>
                            <description></description>	    
                            <attribute>
                              <vodml-id>catalog.SkyCoordinateFrame.name</vodml-id>
                              <name>name</name>
                              <description></description>	    
                              <datatype>
                                 <vodml-ref>ivoa:string</vodml-ref>
                              </datatype>
                              <multiplicity>
                                <minOccurs>1</minOccurs>
                                <maxOccurs>1</maxOccurs>
                              </multiplicity>
                            <constraint xsi:type="vo-dml:NaturalKey">
                            	<position>1</position>
                            </constraint>
                            </attribute>
                            <attribute>
                              <vodml-id>catalog.SkyCoordinateFrame.documentURI</vodml-id>
                              <name>documentURI</name>
                              <description></description>	    
                              <datatype>
                                 <vodml-ref>ivoa:anyURI</vodml-ref>
                              </datatype>
                              <multiplicity>
                                <minOccurs>1</minOccurs>
                                <maxOccurs>1</maxOccurs>
                              </multiplicity>
                            </attribute>
                            <attribute>
                              <vodml-id>catalog.SkyCoordinateFrame.equinox</vodml-id>
                              <name>equinox</name>
                              <description></description>	    
                              <datatype>
                                 <vodml-ref>ivoa:string</vodml-ref>
                              </datatype>
                              <multiplicity>
                                <minOccurs>0</minOccurs>
                                <maxOccurs>1</maxOccurs>
                              </multiplicity>
                            </attribute>
                            <attribute>
                              <vodml-id>catalog.SkyCoordinateFrame.system</vodml-id>
                              <name>system</name>
                              <description></description>	    
                              <datatype>
                                 <vodml-ref>ivoa:string</vodml-ref>
                              </datatype>
                              <multiplicity>
                                <minOccurs>0</minOccurs>
                                <maxOccurs>1</maxOccurs>
                              </multiplicity>
                            </attribute>
                         </objectType>
                         <objectType>
                            <vodml-id>catalog.Source</vodml-id>
                            <name>Source</name>
                            <description></description>	    
                            <extends>
                               <vodml-ref>DemoDM:catalog.AbstractSource</vodml-ref>
                            </extends>
                            <constraint xsi:type="vo-dml:SubsettedRole">
                               <role>
                                  <vodml-ref>DemoDM:catalog.AbstractSource.positionError</vodml-ref>
                               </role>
                               <datatype>
                                  <vodml-ref>DemoDM:catalog.GenericEllipse</vodml-ref>
                               </datatype>
                            </constraint>
                         </objectType>
                         <objectType>
                            <vodml-id>catalog.TwoMassSource</vodml-id>
                            <name>TwoMassSource</name>
                            <description></description>	    
                            <extends>
                               <vodml-ref>DemoDM:catalog.AbstractSource</vodml-ref>
                            </extends>
                            <constraint xsi:type="vo-dml:SubsettedRole">
                               <role>
                                  <vodml-ref>DemoDM:catalog.AbstractSource.positionError</vodml-ref>
                               </role>
                               <datatype>
                                  <vodml-ref>DemoDM:catalog.GenericEllipse</vodml-ref>
                               </datatype>
                            </constraint>
                         </objectType>
                         <package>
                            <vodml-id>catalog.inner</vodml-id>
                            <name>inner</name>
                            <description></description>	    
                                      <objectType>
                                         <vodml-id>catalog.inner.Testing</vodml-id>
                                         <name>Testing</name>
                                         <description></description>	    
                                         <attribute>
                                           <vodml-id>catalog.inner.Testing.plain</vodml-id>
                                           <name>plain</name>
                                           <description>a single string</description>	    
                                           <datatype>
                                              <vodml-ref>ivoa:string</vodml-ref>
                                           </datatype>
                                           <multiplicity>
                                             <minOccurs>1</minOccurs>
                                             <maxOccurs>1</maxOccurs>
                                           </multiplicity>
                                         </attribute>
                                         <attribute>
                                           <vodml-id>catalog.inner.Testing.unbounded</vodml-id>
                                           <name>unbounded</name>
                                           <description>an array with many elements</description>	    
                                           <datatype>
                                              <vodml-ref>ivoa:string</vodml-ref>
                                           </datatype>
                                           <multiplicity>
                                             <minOccurs>0</minOccurs>
                                             <maxOccurs>-1</maxOccurs>
                                           </multiplicity>
                                         </attribute>
                                         <attribute>
                                           <vodml-id>catalog.inner.Testing.apoint</vodml-id>
                                           <name>apoint</name>
                                           <description></description>	    
                                           <datatype>
                                              <vodml-ref>DemoDM:Point</vodml-ref>
                                           </datatype>
                                           <multiplicity>
                                             <minOccurs>1</minOccurs>
                                             <maxOccurs>1</maxOccurs>
                                           </multiplicity>
                                         </attribute>
                                         <attribute>
                                           <vodml-id>catalog.inner.Testing.acircle</vodml-id>
                                           <name>acircle</name>
                                           <description></description>	    
                                           <datatype>
                                              <vodml-ref>DemoDM:Circle</vodml-ref>
                                           </datatype>
                                           <multiplicity>
                                             <minOccurs>1</minOccurs>
                                             <maxOccurs>1</maxOccurs>
                                           </multiplicity>
                                         </attribute>
                                         <attribute>
                                           <vodml-id>catalog.inner.Testing.apoly</vodml-id>
                                           <name>apoly</name>
                                           <description></description>	    
                                           <datatype>
                                              <vodml-ref>DemoDM:Polygon</vodml-ref>
                                           </datatype>
                                           <multiplicity>
                                             <minOccurs>1</minOccurs>
                                             <maxOccurs>1</maxOccurs>
                                           </multiplicity>
                                         </attribute>
                                      </objectType>
                                      <objectType>
                                         <vodml-id>catalog.inner.SourceCatalogue</vodml-id>
                                         <name>SourceCatalogue</name>
                                         <description></description>	    
                                         <attribute>
                                           <vodml-id>catalog.inner.SourceCatalogue.name</vodml-id>
                                           <name>name</name>
                                           <description>the name of the catalogue</description>	    
                                           <datatype>
                                              <vodml-ref>ivoa:string</vodml-ref>
                                           </datatype>
                                           <multiplicity>
                                             <minOccurs>1</minOccurs>
                                             <maxOccurs>1</maxOccurs>
                                           </multiplicity>
                                         </attribute>
                                         <composition>
                                           <vodml-id>catalog.inner.SourceCatalogue.entry</vodml-id>
                                           <name>entry</name>
                                           <description>the entries in the catalogue</description>	    
                                           <datatype>
                                              <vodml-ref>DemoDM:catalog.AbstractSource</vodml-ref>
                                           </datatype>
                                           <multiplicity>
                                             <minOccurs>0</minOccurs>
                                             <maxOccurs>-1</maxOccurs>
                                           </multiplicity>
                                         </composition>
                                         <composition>
                                           <vodml-id>catalog.inner.SourceCatalogue.aTest</vodml-id>
                                           <name>aTest</name>
                                           <description>try this out</description>	    
                                           <datatype>
                                              <vodml-ref>DemoDM:catalog.inner.Testing</vodml-ref>
                                           </datatype>
                                           <multiplicity>
                                             <minOccurs>0</minOccurs>
                                             <maxOccurs>1</maxOccurs>
                                           </multiplicity>
                                         </composition>
                                         <composition>
                                           <vodml-id>catalog.inner.SourceCatalogue.aTestMore</vodml-id>
                                           <name>aTestMore</name>
                                           <description>a try with more than one</description>	    
                                           <datatype>
                                              <vodml-ref>DemoDM:catalog.inner.Testing</vodml-ref>
                                           </datatype>
                                           <multiplicity>
                                             <minOccurs>0</minOccurs>
                                             <maxOccurs>-1</maxOccurs>
                                           </multiplicity>
                                         </composition>
                                      </objectType>
                         </package>
            </package>
</vo-dml:model>
